<?xml version="1.0" encoding="UTF-8"?>
<mxfile host="app.diagrams.net" modified="2023-11-25T18:02:24.462Z" agent="Mozilla/5.0 (Windows NT 10.0; Win64; x64) AppleWebKit/537.36 (KHTML, like Gecko) Chrome/119.0.0.0 Safari/537.36" etag="BEYZPX9bfU43sieULqXc" version="22.1.4" type="google" pages="2">
  <diagram name="1" id="LhEtJ2KfPGMWcfk-PQyk">
    <mxGraphModel dx="1434" dy="760" grid="1" gridSize="10" guides="1" tooltips="1" connect="1" arrows="1" fold="1" page="1" pageScale="1" pageWidth="827" pageHeight="1169" background="#E3E3E3" math="0" shadow="1">
      <root>
        <mxCell id="ewiUAZ0GqBU54c8BVMHp-0" />
        <mxCell id="ewiUAZ0GqBU54c8BVMHp-1" parent="ewiUAZ0GqBU54c8BVMHp-0" />
        <mxCell id="3r-SNJw_MCfYOkOOAU7a-12" value="" style="rounded=0;whiteSpace=wrap;html=1;sketch=1;hachureGap=4;jiggle=2;curveFitting=1;fontFamily=Architects Daughter;fontSource=https%3A%2F%2Ffonts.googleapis.com%2Fcss%3Ffamily%3DArchitects%2BDaughter;fontSize=20;fillColor=none;dashed=1;dashPattern=12 12;" vertex="1" parent="ewiUAZ0GqBU54c8BVMHp-1">
          <mxGeometry x="508" y="340" width="310" height="460" as="geometry" />
        </mxCell>
        <mxCell id="3r-SNJw_MCfYOkOOAU7a-11" value="" style="rounded=0;whiteSpace=wrap;html=1;sketch=1;hachureGap=4;jiggle=2;curveFitting=1;fontFamily=Architects Daughter;fontSource=https%3A%2F%2Ffonts.googleapis.com%2Fcss%3Ffamily%3DArchitects%2BDaughter;fontSize=20;fillColor=none;dashed=1;dashPattern=12 12;" vertex="1" parent="ewiUAZ0GqBU54c8BVMHp-1">
          <mxGeometry x="10" y="340" width="310" height="460" as="geometry" />
        </mxCell>
        <mxCell id="ewiUAZ0GqBU54c8BVMHp-2" value="" style="shape=image;imageAspect=0;aspect=fixed;verticalLabelPosition=bottom;verticalAlign=top;rounded=0;sketch=0;strokeColor=#FF6392;fillColor=#FFE45E;fontColor=#5AA9E6;image=https://cursos-dev.com/assets/images/logo-horizontal.png;" parent="ewiUAZ0GqBU54c8BVMHp-1" vertex="1">
          <mxGeometry width="282.99" height="80" as="geometry" />
        </mxCell>
        <mxCell id="3r-SNJw_MCfYOkOOAU7a-2" value="" style="edgeStyle=orthogonalEdgeStyle;rounded=0;sketch=1;hachureGap=4;jiggle=2;curveFitting=1;orthogonalLoop=1;jettySize=auto;html=1;fontFamily=Architects Daughter;fontSource=https%3A%2F%2Ffonts.googleapis.com%2Fcss%3Ffamily%3DArchitects%2BDaughter;fontSize=16;" edge="1" parent="ewiUAZ0GqBU54c8BVMHp-1" source="3r-SNJw_MCfYOkOOAU7a-0" target="3r-SNJw_MCfYOkOOAU7a-1">
          <mxGeometry relative="1" as="geometry" />
        </mxCell>
        <mxCell id="3r-SNJw_MCfYOkOOAU7a-4" style="edgeStyle=orthogonalEdgeStyle;rounded=0;sketch=1;hachureGap=4;jiggle=2;curveFitting=1;orthogonalLoop=1;jettySize=auto;html=1;exitX=1;exitY=0.5;exitDx=0;exitDy=0;entryX=0.5;entryY=0;entryDx=0;entryDy=0;fontFamily=Architects Daughter;fontSource=https%3A%2F%2Ffonts.googleapis.com%2Fcss%3Ffamily%3DArchitects%2BDaughter;fontSize=16;" edge="1" parent="ewiUAZ0GqBU54c8BVMHp-1" source="3r-SNJw_MCfYOkOOAU7a-0" target="3r-SNJw_MCfYOkOOAU7a-3">
          <mxGeometry relative="1" as="geometry" />
        </mxCell>
        <mxCell id="3r-SNJw_MCfYOkOOAU7a-0" value="class Perro" style="rounded=0;whiteSpace=wrap;html=1;sketch=1;hachureGap=4;jiggle=2;curveFitting=1;fontFamily=Architects Daughter;fontSource=https%3A%2F%2Ffonts.googleapis.com%2Fcss%3Ffamily%3DArchitects%2BDaughter;fontSize=20;fillColor=#f8cecc;strokeColor=#b85450;" vertex="1" parent="ewiUAZ0GqBU54c8BVMHp-1">
          <mxGeometry x="294" y="200" width="226" height="60" as="geometry" />
        </mxCell>
        <mxCell id="3r-SNJw_MCfYOkOOAU7a-6" value="" style="edgeStyle=orthogonalEdgeStyle;rounded=0;sketch=1;hachureGap=4;jiggle=2;curveFitting=1;orthogonalLoop=1;jettySize=auto;html=1;fontFamily=Architects Daughter;fontSource=https%3A%2F%2Ffonts.googleapis.com%2Fcss%3Ffamily%3DArchitects%2BDaughter;fontSize=16;" edge="1" parent="ewiUAZ0GqBU54c8BVMHp-1" source="3r-SNJw_MCfYOkOOAU7a-1" target="3r-SNJw_MCfYOkOOAU7a-5">
          <mxGeometry relative="1" as="geometry" />
        </mxCell>
        <mxCell id="3r-SNJw_MCfYOkOOAU7a-1" value="new Perro()" style="rounded=0;whiteSpace=wrap;html=1;sketch=1;hachureGap=4;jiggle=2;curveFitting=1;fontFamily=Architects Daughter;fontSource=https%3A%2F%2Ffonts.googleapis.com%2Fcss%3Ffamily%3DArchitects%2BDaughter;fontSize=20;fillColor=#e1d5e7;strokeColor=#9673a6;" vertex="1" parent="ewiUAZ0GqBU54c8BVMHp-1">
          <mxGeometry x="40" y="400" width="226" height="60" as="geometry" />
        </mxCell>
        <mxCell id="3r-SNJw_MCfYOkOOAU7a-8" value="" style="edgeStyle=orthogonalEdgeStyle;rounded=0;sketch=1;hachureGap=4;jiggle=2;curveFitting=1;orthogonalLoop=1;jettySize=auto;html=1;fontFamily=Architects Daughter;fontSource=https%3A%2F%2Ffonts.googleapis.com%2Fcss%3Ffamily%3DArchitects%2BDaughter;fontSize=16;" edge="1" parent="ewiUAZ0GqBU54c8BVMHp-1" source="3r-SNJw_MCfYOkOOAU7a-3" target="3r-SNJw_MCfYOkOOAU7a-7">
          <mxGeometry relative="1" as="geometry" />
        </mxCell>
        <mxCell id="3r-SNJw_MCfYOkOOAU7a-3" value="new Perro()" style="rounded=0;whiteSpace=wrap;html=1;sketch=1;hachureGap=4;jiggle=2;curveFitting=1;fontFamily=Architects Daughter;fontSource=https%3A%2F%2Ffonts.googleapis.com%2Fcss%3Ffamily%3DArchitects%2BDaughter;fontSize=20;fillColor=#e1d5e7;strokeColor=#9673a6;" vertex="1" parent="ewiUAZ0GqBU54c8BVMHp-1">
          <mxGeometry x="550" y="400" width="226" height="60" as="geometry" />
        </mxCell>
        <mxCell id="3r-SNJw_MCfYOkOOAU7a-10" value="" style="edgeStyle=orthogonalEdgeStyle;rounded=0;sketch=1;hachureGap=4;jiggle=2;curveFitting=1;orthogonalLoop=1;jettySize=auto;html=1;fontFamily=Architects Daughter;fontSource=https%3A%2F%2Ffonts.googleapis.com%2Fcss%3Ffamily%3DArchitects%2BDaughter;fontSize=16;" edge="1" parent="ewiUAZ0GqBU54c8BVMHp-1" source="3r-SNJw_MCfYOkOOAU7a-5" target="3r-SNJw_MCfYOkOOAU7a-9">
          <mxGeometry relative="1" as="geometry" />
        </mxCell>
        <mxCell id="3r-SNJw_MCfYOkOOAU7a-5" value="raza = &quot;Doberman&quot;" style="rounded=0;whiteSpace=wrap;html=1;sketch=1;hachureGap=4;jiggle=2;curveFitting=1;fontFamily=Architects Daughter;fontSource=https%3A%2F%2Ffonts.googleapis.com%2Fcss%3Ffamily%3DArchitects%2BDaughter;fontSize=20;fillColor=#fff2cc;strokeColor=#d6b656;" vertex="1" parent="ewiUAZ0GqBU54c8BVMHp-1">
          <mxGeometry x="40" y="540" width="226" height="60" as="geometry" />
        </mxCell>
        <mxCell id="3r-SNJw_MCfYOkOOAU7a-7" value="raza = &quot;Samoyedo&quot;" style="rounded=0;whiteSpace=wrap;html=1;sketch=1;hachureGap=4;jiggle=2;curveFitting=1;fontFamily=Architects Daughter;fontSource=https%3A%2F%2Ffonts.googleapis.com%2Fcss%3Ffamily%3DArchitects%2BDaughter;fontSize=20;fillColor=#fff2cc;strokeColor=#d6b656;" vertex="1" parent="ewiUAZ0GqBU54c8BVMHp-1">
          <mxGeometry x="550" y="540" width="226" height="60" as="geometry" />
        </mxCell>
        <mxCell id="3r-SNJw_MCfYOkOOAU7a-9" value="raza = &quot;DOBERMAN&quot;" style="rounded=0;whiteSpace=wrap;html=1;sketch=1;hachureGap=4;jiggle=2;curveFitting=1;fontFamily=Architects Daughter;fontSource=https%3A%2F%2Ffonts.googleapis.com%2Fcss%3Ffamily%3DArchitects%2BDaughter;fontSize=20;fillColor=#fff2cc;strokeColor=#d6b656;" vertex="1" parent="ewiUAZ0GqBU54c8BVMHp-1">
          <mxGeometry x="40" y="680" width="226" height="60" as="geometry" />
        </mxCell>
      </root>
    </mxGraphModel>
  </diagram>
  <diagram name="2" id="prMRHyn3zO79hluYMLMS">
    <mxGraphModel dx="1434" dy="760" grid="1" gridSize="10" guides="1" tooltips="1" connect="1" arrows="1" fold="1" page="1" pageScale="1" pageWidth="827" pageHeight="1169" background="#E3E3E3" math="0" shadow="1">
      <root>
        <mxCell id="zrl8X_l8YgIph6KKR3ua-0" />
        <mxCell id="zrl8X_l8YgIph6KKR3ua-1" parent="zrl8X_l8YgIph6KKR3ua-0" />
        <mxCell id="zrl8X_l8YgIph6KKR3ua-4" value="" style="shape=image;imageAspect=0;aspect=fixed;verticalLabelPosition=bottom;verticalAlign=top;rounded=0;sketch=0;strokeColor=#FF6392;fillColor=#FFE45E;fontColor=#5AA9E6;image=https://cursos-dev.com/assets/images/logo-horizontal.png;" vertex="1" parent="zrl8X_l8YgIph6KKR3ua-1">
          <mxGeometry width="282.99" height="80" as="geometry" />
        </mxCell>
        <mxCell id="h4TVojm1yA5rfih_OoM_-2" value="" style="edgeStyle=orthogonalEdgeStyle;rounded=0;sketch=1;hachureGap=4;jiggle=2;curveFitting=1;orthogonalLoop=1;jettySize=auto;html=1;fontFamily=Architects Daughter;fontSource=https%3A%2F%2Ffonts.googleapis.com%2Fcss%3Ffamily%3DArchitects%2BDaughter;fontSize=16;" edge="1" parent="zrl8X_l8YgIph6KKR3ua-1" source="h4TVojm1yA5rfih_OoM_-0" target="h4TVojm1yA5rfih_OoM_-1">
          <mxGeometry relative="1" as="geometry" />
        </mxCell>
        <mxCell id="h4TVojm1yA5rfih_OoM_-4" value="" style="edgeStyle=orthogonalEdgeStyle;rounded=0;sketch=1;hachureGap=4;jiggle=2;curveFitting=1;orthogonalLoop=1;jettySize=auto;html=1;fontFamily=Architects Daughter;fontSource=https%3A%2F%2Ffonts.googleapis.com%2Fcss%3Ffamily%3DArchitects%2BDaughter;fontSize=16;" edge="1" parent="zrl8X_l8YgIph6KKR3ua-1" source="h4TVojm1yA5rfih_OoM_-0" target="h4TVojm1yA5rfih_OoM_-3">
          <mxGeometry relative="1" as="geometry" />
        </mxCell>
        <mxCell id="h4TVojm1yA5rfih_OoM_-6" value="" style="edgeStyle=orthogonalEdgeStyle;rounded=0;sketch=1;hachureGap=4;jiggle=2;curveFitting=1;orthogonalLoop=1;jettySize=auto;html=1;fontFamily=Architects Daughter;fontSource=https%3A%2F%2Ffonts.googleapis.com%2Fcss%3Ffamily%3DArchitects%2BDaughter;fontSize=16;" edge="1" parent="zrl8X_l8YgIph6KKR3ua-1" source="h4TVojm1yA5rfih_OoM_-0" target="h4TVojm1yA5rfih_OoM_-5">
          <mxGeometry relative="1" as="geometry" />
        </mxCell>
        <mxCell id="h4TVojm1yA5rfih_OoM_-0" value="Modificadores de acceso" style="rounded=0;whiteSpace=wrap;html=1;sketch=1;hachureGap=4;jiggle=2;curveFitting=1;fontFamily=Architects Daughter;fontSource=https%3A%2F%2Ffonts.googleapis.com%2Fcss%3Ffamily%3DArchitects%2BDaughter;fontSize=20;fillColor=#f8cecc;strokeColor=#b85450;" vertex="1" parent="zrl8X_l8YgIph6KKR3ua-1">
          <mxGeometry x="320" y="320" width="216" height="60" as="geometry" />
        </mxCell>
        <mxCell id="h4TVojm1yA5rfih_OoM_-1" value="Public" style="rounded=0;whiteSpace=wrap;html=1;sketch=1;hachureGap=4;jiggle=2;curveFitting=1;fontFamily=Architects Daughter;fontSource=https%3A%2F%2Ffonts.googleapis.com%2Fcss%3Ffamily%3DArchitects%2BDaughter;fontSize=20;fillColor=#d5e8d4;strokeColor=#82b366;" vertex="1" parent="zrl8X_l8YgIph6KKR3ua-1">
          <mxGeometry x="78" y="500" width="216" height="60" as="geometry" />
        </mxCell>
        <mxCell id="h4TVojm1yA5rfih_OoM_-3" value="Private" style="rounded=0;whiteSpace=wrap;html=1;sketch=1;hachureGap=4;jiggle=2;curveFitting=1;fontFamily=Architects Daughter;fontSource=https%3A%2F%2Ffonts.googleapis.com%2Fcss%3Ffamily%3DArchitects%2BDaughter;fontSize=20;fillColor=#d5e8d4;strokeColor=#82b366;" vertex="1" parent="zrl8X_l8YgIph6KKR3ua-1">
          <mxGeometry x="320" y="500" width="216" height="60" as="geometry" />
        </mxCell>
        <mxCell id="h4TVojm1yA5rfih_OoM_-5" value="Protected" style="rounded=0;whiteSpace=wrap;html=1;sketch=1;hachureGap=4;jiggle=2;curveFitting=1;fontFamily=Architects Daughter;fontSource=https%3A%2F%2Ffonts.googleapis.com%2Fcss%3Ffamily%3DArchitects%2BDaughter;fontSize=20;fillColor=#d5e8d4;strokeColor=#82b366;" vertex="1" parent="zrl8X_l8YgIph6KKR3ua-1">
          <mxGeometry x="560" y="500" width="216" height="60" as="geometry" />
        </mxCell>
      </root>
    </mxGraphModel>
  </diagram>
</mxfile>
